blesonwin.cp39-win_amd64.pyd
blesonwin-0.0.12.dist-info/METADATA
blesonwin-0.0.12.dist-info/WHEEL
blesonwin-0.0.12.dist-info/top_level.txt
blesonwin-0.0.12.dist-info/RECORD
